circular_dict/CircularDict.py
circular_dict/__init__.py
circular_dict-1.9.dist-info/LICENSE
circular_dict-1.9.dist-info/METADATA
circular_dict-1.9.dist-info/WHEEL
circular_dict-1.9.dist-info/top_level.txt
circular_dict-1.9.dist-info/RECORD
