Metadata-Version: 2.1
Name: circular-dict
Version: 1.9
Summary: CircularDict is a high-performance Python data structure that blends the functionality of dictionaries and circular buffers. Inheriting the usage of traditional dictionaries, it allows you to define constraints on size and memory usage. This way, the CircularDict will be always up-to-date with the last N added elements, ensuring that neither the maximum length nor the memory usage limit is exceeded. It is ideal for caching large data structures while maintaining control over memory foot
Home-page: https://github.com/Eric-Canas/CircularDict
Author: Eric-Canas
Author-email: eric@ericcanas.com
License: MIT
Classifier: Development Status :: 5 - Production/Stable
Classifier: License :: OSI Approved :: MIT License
Classifier: Programming Language :: Python
Classifier: Programming Language :: Python :: 3
Classifier: Programming Language :: Python :: 3.6
Classifier: Programming Language :: Python :: 3.7
Classifier: Programming Language :: Python :: 3.8
Classifier: Programming Language :: Python :: 3.9
Classifier: Programming Language :: Python :: 3.10
Classifier: Operating System :: OS Independent
Classifier: Intended Audience :: Developers
Classifier: Topic :: Software Development :: Libraries
Classifier: Topic :: Software Development :: Libraries :: Python Modules
Classifier: Topic :: Utilities
Classifier: Topic :: System :: Hardware
Classifier: Topic :: Software Development :: Testing
Classifier: Topic :: Software Development :: Debuggers
Requires-Python: >=3.6
License-File: LICENSE
